<?xml version="1.0" encoding="utf-8"?>
<clothing-items>
 <clothing>
  <id>
   451621302
  </id>
  <name>
   Addidas Umbrellas M-5589
  </name>
  <category>
   Umbrellas
  </category>
  <size>
   XXL
  </size>
  <color>
   Желтый
  </color>
  <material>
   Вискоза
  </material>
  <price>
   491468
  </price>
  <rating>
   4.82
  </rating>
  <reviews>
   911297
  </reviews>
  <exclusive>
   no
  </exclusive>
  <sporty>
   no
  </sporty>
 </clothing>
 <clothing>
  <id>
   525781822
  </id>
  <name>
   PleinSport T-shirt B-5469
  </name>
  <category>
   T-shirt
  </category>
  <size>
   XXL
  </size>
  <color>
   Синий
  </color>
  <material>
   Полиэстер
  </material>
  <price>
   896756
  </price>
  <rating>
   1.01
  </rating>
  <reviews>
   627968
  </reviews>
  <exclusive>
   no
  </exclusive>
  <sporty>
   no
  </sporty>
 </clothing>
 <clothing>
  <id>
   420494663
  </id>
  <name>
   Brooks T-shirt M-2866
  </name>
  <category>
   T-shirt
  </category>
  <size>
   S
  </size>
  <color>
   Зеленый
  </color>
  <material>
   Полиэстер
  </material>
  <price>
   220950
  </price>
  <rating>
   1.75
  </rating>
  <reviews>
   659894
  </reviews>
  <new>
   -
  </new>
  <sporty>
   yes
  </sporty>
 </clothing>
 <clothing>
  <id>
   865525258
  </id>
  <name>
   Under Armour Jacket F-5518
  </name>
  <category>
   Jacket
  </category>
  <size>
   L
  </size>
  <color>
   Красный
  </color>
  <material>
   Вискоза
  </material>
  <price>
   226077
  </price>
  <rating>
   2.07
  </rating>
  <reviews>
   665964
  </reviews>
  <exclusive>
   yes
  </exclusive>
  <sporty>
   yes
  </sporty>
 </clothing>
 <clothing>
  <id>
   620774175
  </id>
  <name>
   Converse Socks U-7611
  </name>
  <category>
   Socks
  </category>
  <size>
   L
  </size>
  <color>
   Зеленый
  </color>
  <material>
   Кожа
  </material>
  <price>
   471975
  </price>
  <rating>
   4.51
  </rating>
  <reviews>
   41483
  </reviews>
  <sporty>
   yes
  </sporty>
 </clothing>
 <clothing>
  <id>
   488617005
  </id>
  <name>
   Brooks Handbags K-4322
  </name>
  <category>
   Handbags
  </category>
  <size>
   L
  </size>
  <color>
   Синий
  </color>
  <material>
   Шелк
  </material>
  <price>
   109463
  </price>
  <rating>
   1.92
  </rating>
  <reviews>
   943568
  </reviews>
  <sporty>
   no
  </sporty>
 </clothing>
 <clothing>
  <id>
   896631179
  </id>
  <name>
   Reebok Jeans K-4918
  </name>
  <category>
   Jeans
  </category>
  <size>
   XXL
  </size>
  <color>
   Голубой
  </color>
  <material>
   Хлопок
  </material>
  <price>
   941699
  </price>
  <rating>
   2.14
  </rating>
  <reviews>
   75635
  </reviews>
  <new>
   +
  </new>
 </clothing>
 <clothing>
  <id>
   497756143
  </id>
  <name>
   Nike Gloves J-2632
  </name>
  <category>
   Gloves
  </category>
  <size>
   L
  </size>
  <color>
   Зеленый
  </color>
  <material>
   Вискоза
  </material>
  <price>
   539110
  </price>
  <rating>
   2.85
  </rating>
  <reviews>
   712958
  </reviews>
  <new>
   -
  </new>
 </clothing>
 <clothing>
  <id>
   340501429
  </id>
  <name>
   PleinSport Shirt D-3062
  </name>
  <category>
   Shirt
  </category>
  <size>
   S
  </size>
  <color>
   Синий
  </color>
  <material>
   Вискоза
  </material>
  <price>
   700165
  </price>
  <rating>
   1.17
  </rating>
  <reviews>
   809374
  </reviews>
  <new>
   -
  </new>
  <exclusive>
   no
  </exclusive>
  <sporty>
   yes
  </sporty>
 </clothing>
 <clothing>
  <id>
   513842640
  </id>
  <name>
   Nike Belts D-8963
  </name>
  <category>
   Belts
  </category>
  <size>
   XL
  </size>
  <color>
   Фиолетовый
  </color>
  <material>
   Нейлон
  </material>
  <price>
   697440
  </price>
  <rating>
   4.98
  </rating>
  <reviews>
   366485
  </reviews>
  <new>
   +
  </new>
  <exclusive>
   yes
  </exclusive>
  <sporty>
   yes
  </sporty>
 </clothing>
 <clothing>
  <id>
   503013898
  </id>
  <name>
   Adidas Socks K-4985
  </name>
  <category>
   Socks
  </category>
  <size>
   M
  </size>
  <color>
   Голубой
  </color>
  <material>
   Шелк
  </material>
  <price>
   911000
  </price>
  <rating>
   1.89
  </rating>
  <reviews>
   963930
  </reviews>
  <exclusive>
   no
  </exclusive>
  <sporty>
   no
  </sporty>
 </clothing>
 <clothing>
  <id>
   904823739
  </id>
  <name>
   Under Armour Jacket X-2073
  </name>
  <category>
   Jacket
  </category>
  <size>
   M
  </size>
  <color>
   Желтый
  </color>
  <material>
   Кожа
  </material>
  <price>
   215168
  </price>
  <rating>
   4.39
  </rating>
  <reviews>
   221226
  </reviews>
  <new>
   -
  </new>
  <exclusive>
   no
  </exclusive>
  <sporty>
   no
  </sporty>
 </clothing>
 <clothing>
  <id>
   735301083
  </id>
  <name>
   New Balance Pants Z-5276
  </name>
  <category>
   Pants
  </category>
  <size>
   S
  </size>
  <color>
   Красный
  </color>
  <material>
   Кожа
  </material>
  <price>
   696012
  </price>
  <rating>
   3.22
  </rating>
  <reviews>
   28020
  </reviews>
  <new>
   +
  </new>
  <exclusive>
   yes
  </exclusive>
  <sporty>
   no
  </sporty>
 </clothing>
 <clothing>
  <id>
   568044838
  </id>
  <name>
   Nike Pants W-7768
  </name>
  <category>
   Pants
  </category>
  <size>
   S
  </size>
  <color>
   Голубой
  </color>
  <material>
   Шерсть
  </material>
  <price>
   274822
  </price>
  <rating>
   3.74
  </rating>
  <reviews>
   54871
  </reviews>
  <new>
   +
  </new>
  <sporty>
   no
  </sporty>
 </clothing>
 <clothing>
  <id>
   375857187
  </id>
  <name>
   Converse Jacket Q-4305
  </name>
  <category>
   Jacket
  </category>
  <size>
   L
  </size>
  <color>
   Оранжевый
  </color>
  <material>
   Шерсть
  </material>
  <price>
   268583
  </price>
  <rating>
   2.8
  </rating>
  <reviews>
   64430
  </reviews>
  <new>
   +
  </new>
 </clothing>
 <clothing>
  <id>
   516403893
  </id>
  <name>
   Nike Gloves X-3828
  </name>
  <category>
   Gloves
  </category>
  <size>
   M
  </size>
  <color>
   Зеленый
  </color>
  <material>
   Полиэстер
  </material>
  <price>
   182816
  </price>
  <rating>
   2.97
  </rating>
  <reviews>
   96204
  </reviews>
  <new>
   -
  </new>
  <sporty>
   no
  </sporty>
 </clothing>
 <clothing>
  <id>
   177788227
  </id>
  <name>
   Nike Hat X-4394
  </name>
  <category>
   Hat
  </category>
  <size>
   M
  </size>
  <color>
   Желтый
  </color>
  <material>
   Шелк
  </material>
  <price>
   819671
  </price>
  <rating>
   3.1
  </rating>
  <reviews>
   893475
  </reviews>
  <new>
   -
  </new>
  <sporty>
   no
  </sporty>
 </clothing>
 <clothing>
  <id>
   375259633
  </id>
  <name>
   New Balance Umbrellas O-3450
  </name>
  <category>
   Umbrellas
  </category>
  <size>
   L
  </size>
  <color>
   Голубой
  </color>
  <material>
   Хлопок
  </material>
  <price>
   338501
  </price>
  <rating>
   4.62
  </rating>
  <reviews>
   322120
  </reviews>
  <new>
   -
  </new>
 </clothing>
 <clothing>
  <id>
   880126946
  </id>
  <name>
   Addidas Jacket X-8824
  </name>
  <category>
   Jacket
  </category>
  <size>
   XXL
  </size>
  <color>
   Красный
  </color>
  <material>
   Хлопок
  </material>
  <price>
   181500
  </price>
  <rating>
   2.63
  </rating>
  <reviews>
   309281
  </reviews>
  <new>
   -
  </new>
  <exclusive>
   no
  </exclusive>
 </clothing>
 <clothing>
  <id>
   103331409
  </id>
  <name>
   Fila Dress M-6489
  </name>
  <category>
   Dress
  </category>
  <size>
   S
  </size>
  <color>
   Фиолетовый
  </color>
  <material>
   Полиэстер
  </material>
  <price>
   327455
  </price>
  <rating>
   3.82
  </rating>
  <reviews>
   842499
  </reviews>
  <new>
   +
  </new>
  <exclusive>
   yes
  </exclusive>
 </clothing>
 <clothing>
  <id>
   416649579
  </id>
  <name>
   PleinSport Socks R-1011
  </name>
  <category>
   Socks
  </category>
  <size>
   M
  </size>
  <color>
   Оранжевый
  </color>
  <material>
   Кожа
  </material>
  <price>
   390663
  </price>
  <rating>
   3.67
  </rating>
  <reviews>
   138444
  </reviews>
  <sporty>
   no
  </sporty>
 </clothing>
 <clothing>
  <id>
   844823018
  </id>
  <name>
   Converse Umbrellas J-5952
  </name>
  <category>
   Umbrellas
  </category>
  <size>
   XL
  </size>
  <color>
   Фиолетовый
  </color>
  <material>
   Шелк
  </material>
  <price>
   378520
  </price>
  <rating>
   3.51
  </rating>
  <reviews>
   88359
  </reviews>
 </clothing>
 <clothing>
  <id>
   138810836
  </id>
  <name>
   Converse Shirt O-2266
  </name>
  <category>
   Shirt
  </category>
  <size>
   S
  </size>
  <color>
   Синий
  </color>
  <material>
   Шерсть
  </material>
  <price>
   260825
  </price>
  <rating>
   4.82
  </rating>
  <reviews>
   89344
  </reviews>
  <new>
   +
  </new>
  <sporty>
   no
  </sporty>
 </clothing>
 <clothing>
  <id>
   189140071
  </id>
  <name>
   Lacoste Jacket Q-1738
  </name>
  <category>
   Jacket
  </category>
  <size>
   L
  </size>
  <color>
   Синий
  </color>
  <material>
   Лен
  </material>
  <price>
   292984
  </price>
  <rating>
   2.95
  </rating>
  <reviews>
   266440
  </reviews>
  <new>
   +
  </new>
  <exclusive>
   no
  </exclusive>
  <sporty>
   no
  </sporty>
 </clothing>
 <clothing>
  <id>
   215185885
  </id>
  <name>
   Fila Jeans K-3897
  </name>
  <category>
   Jeans
  </category>
  <size>
   XXL
  </size>
  <color>
   Голубой
  </color>
  <material>
   Лен
  </material>
  <price>
   411646
  </price>
  <rating>
   3.95
  </rating>
  <reviews>
   563167
  </reviews>
  <exclusive>
   no
  </exclusive>
 </clothing>
 <clothing>
  <id>
   676108084
  </id>
  <name>
   Reebok Hat H-4612
  </name>
  <category>
   Hat
  </category>
  <size>
   S
  </size>
  <color>
   Желтый
  </color>
  <material>
   Лен
  </material>
  <price>
   444970
  </price>
  <rating>
   4.51
  </rating>
  <reviews>
   972758
  </reviews>
  <new>
   -
  </new>
  <sporty>
   no
  </sporty>
 </clothing>
 <clothing>
  <id>
   318119924
  </id>
  <name>
   Fila Dress E-6552
  </name>
  <category>
   Dress
  </category>
  <size>
   L
  </size>
  <color>
   Зеленый
  </color>
  <material>
   Лен
  </material>
  <price>
   785437
  </price>
  <rating>
   1.66
  </rating>
  <reviews>
   224643
  </reviews>
  <new>
   -
  </new>
  <exclusive>
   no
  </exclusive>
 </clothing>
 <clothing>
  <id>
   112291457
  </id>
  <name>
   Vans Jacket V-2470
  </name>
  <category>
   Jacket
  </category>
  <size>
   S
  </size>
  <color>
   Зеленый
  </color>
  <material>
   Полиэстер
  </material>
  <price>
   460681
  </price>
  <rating>
   3.49
  </rating>
  <reviews>
   812090
  </reviews>
  <new>
   +
  </new>
 </clothing>
 <clothing>
  <id>
   873467568
  </id>
  <name>
   Brooks Pants N-7421
  </name>
  <category>
   Pants
  </category>
  <size>
   XXL
  </size>
  <color>
   Синий
  </color>
  <material>
   Хлопок
  </material>
  <price>
   729134
  </price>
  <rating>
   4.81
  </rating>
  <reviews>
   426143
  </reviews>
  <new>
   -
  </new>
  <sporty>
   no
  </sporty>
 </clothing>
 <clothing>
  <id>
   814701194
  </id>
  <name>
   Addidas Sweater T-7514
  </name>
  <category>
   Sweater
  </category>
  <size>
   XL
  </size>
  <color>
   Голубой
  </color>
  <material>
   Нейлон
  </material>
  <price>
   527555
  </price>
  <rating>
   3.42
  </rating>
  <reviews>
   494953
  </reviews>
  <new>
   +
  </new>
  <exclusive>
   no
  </exclusive>
  <sporty>
   no
  </sporty>
 </clothing>
 <clothing>
  <id>
   405949715
  </id>
  <name>
   Addidas Belts Q-6009
  </name>
  <category>
   Belts
  </category>
  <size>
   L
  </size>
  <color>
   Фиолетовый
  </color>
  <material>
   Хлопок
  </material>
  <price>
   709477
  </price>
  <rating>
   4.26
  </rating>
  <reviews>
   773832
  </reviews>
  <new>
   +
  </new>
 </clothing>
 <clothing>
  <id>
   252465552
  </id>
  <name>
   DC T-shirt D-5598
  </name>
  <category>
   T-shirt
  </category>
  <size>
   M
  </size>
  <color>
   Голубой
  </color>
  <material>
   Шерсть
  </material>
  <price>
   578807
  </price>
  <rating>
   2.66
  </rating>
  <reviews>
   904255
  </reviews>
  <new>
   +
  </new>
  <sporty>
   yes
  </sporty>
 </clothing>
 <clothing>
  <id>
   800893512
  </id>
  <name>
   Asics Jeans X-5668
  </name>
  <category>
   Jeans
  </category>
  <size>
   XL
  </size>
  <color>
   Голубой
  </color>
  <material>
   Шерсть
  </material>
  <price>
   885075
  </price>
  <rating>
   1.86
  </rating>
  <reviews>
   135651
  </reviews>
  <sporty>
   yes
  </sporty>
 </clothing>
 <clothing>
  <id>
   867080783
  </id>
  <name>
   Puma Handbags R-7542
  </name>
  <category>
   Handbags
  </category>
  <size>
   XL
  </size>
  <color>
   Голубой
  </color>
  <material>
   Хлопок
  </material>
  <price>
   448039
  </price>
  <rating>
   3.93
  </rating>
  <reviews>
   206718
  </reviews>
  <new>
   -
  </new>
 </clothing>
 <clothing>
  <id>
   196741887
  </id>
  <name>
   DC Gloves Y-5920
  </name>
  <category>
   Gloves
  </category>
  <size>
   XXL
  </size>
  <color>
   Фиолетовый
  </color>
  <material>
   Шелк
  </material>
  <price>
   569666
  </price>
  <rating>
   3.93
  </rating>
  <reviews>
   359572
  </reviews>
  <sporty>
   no
  </sporty>
 </clothing>
 <clothing>
  <id>
   582179719
  </id>
  <name>
   Nike Gloves D-3441
  </name>
  <category>
   Gloves
  </category>
  <size>
   XL
  </size>
  <color>
   Желтый
  </color>
  <material>
   Кожа
  </material>
  <price>
   407205
  </price>
  <rating>
   4.43
  </rating>
  <reviews>
   272954
  </reviews>
 </clothing>
 <clothing>
  <id>
   591115029
  </id>
  <name>
   Lacoste Hat B-4493
  </name>
  <category>
   Hat
  </category>
  <size>
   XL
  </size>
  <color>
   Зеленый
  </color>
  <material>
   Нейлон
  </material>
  <price>
   592302
  </price>
  <rating>
   1.25
  </rating>
  <reviews>
   217285
  </reviews>
  <new>
   -
  </new>
 </clothing>
 <clothing>
  <id>
   524682066
  </id>
  <name>
   Fila Umbrellas K-1708
  </name>
  <category>
   Umbrellas
  </category>
  <size>
   XXL
  </size>
  <color>
   Красный
  </color>
  <material>
   Полиэстер
  </material>
  <price>
   742272
  </price>
  <rating>
   1.58
  </rating>
  <reviews>
   220076
  </reviews>
  <new>
   +
  </new>
  <exclusive>
   no
  </exclusive>
 </clothing>
 <clothing>
  <id>
   569644282
  </id>
  <name>
   Lacoste Blouse J-4945
  </name>
  <category>
   Blouse
  </category>
  <size>
   XL
  </size>
  <color>
   Фиолетовый
  </color>
  <material>
   Шерсть
  </material>
  <price>
   888692
  </price>
  <rating>
   1.77
  </rating>
  <reviews>
   777435
  </reviews>
  <new>
   -
  </new>
  <exclusive>
   no
  </exclusive>
  <sporty>
   yes
  </sporty>
 </clothing>
 <clothing>
  <id>
   617096470
  </id>
  <name>
   Addidas Handbags J-2651
  </name>
  <category>
   Handbags
  </category>
  <size>
   XL
  </size>
  <color>
   Голубой
  </color>
  <material>
   Шелк
  </material>
  <price>
   659394
  </price>
  <rating>
   3.93
  </rating>
  <reviews>
   700846
  </reviews>
  <exclusive>
   no
  </exclusive>
  <sporty>
   no
  </sporty>
 </clothing>
 <clothing>
  <id>
   152913671
  </id>
  <name>
   Addidas Hat F-8973
  </name>
  <category>
   Hat
  </category>
  <size>
   XL
  </size>
  <color>
   Оранжевый
  </color>
  <material>
   Шелк
  </material>
  <price>
   775810
  </price>
  <rating>
   4.08
  </rating>
  <reviews>
   783786
  </reviews>
  <new>
   -
  </new>
  <sporty>
   yes
  </sporty>
 </clothing>
 <clothing>
  <id>
   718451581
  </id>
  <name>
   Puma Shirt T-8671
  </name>
  <category>
   Shirt
  </category>
  <size>
   L
  </size>
  <color>
   Оранжевый
  </color>
  <material>
   Вискоза
  </material>
  <price>
   561677
  </price>
  <rating>
   4.85
  </rating>
  <reviews>
   475901
  </reviews>
  <exclusive>
   no
  </exclusive>
 </clothing>
 <clothing>
  <id>
   330563167
  </id>
  <name>
   Adidas Blouse I-5240
  </name>
  <category>
   Blouse
  </category>
  <size>
   M
  </size>
  <color>
   Синий
  </color>
  <material>
   Лен
  </material>
  <price>
   138630
  </price>
  <rating>
   1.41
  </rating>
  <reviews>
   483791
  </reviews>
  <exclusive>
   yes
  </exclusive>
 </clothing>
 <clothing>
  <id>
   386255395
  </id>
  <name>
   DC Hat X-3623
  </name>
  <category>
   Hat
  </category>
  <size>
   XXL
  </size>
  <color>
   Синий
  </color>
  <material>
   Вискоза
  </material>
  <price>
   419147
  </price>
  <rating>
   1.18
  </rating>
  <reviews>
   359242
  </reviews>
  <exclusive>
   yes
  </exclusive>
  <sporty>
   no
  </sporty>
 </clothing>
 <clothing>
  <id>
   258595909
  </id>
  <name>
   Nike Shoes G-4623
  </name>
  <category>
   Shoes
  </category>
  <size>
   S
  </size>
  <color>
   Красный
  </color>
  <material>
   Вискоза
  </material>
  <price>
   468158
  </price>
  <rating>
   4.55
  </rating>
  <reviews>
   775765
  </reviews>
  <new>
   -
  </new>
  <exclusive>
   no
  </exclusive>
 </clothing>
 <clothing>
  <id>
   822667854
  </id>
  <name>
   Under Armour Handbags T-9939
  </name>
  <category>
   Handbags
  </category>
  <size>
   M
  </size>
  <color>
   Желтый
  </color>
  <material>
   Полиэстер
  </material>
  <price>
   419870
  </price>
  <rating>
   4.21
  </rating>
  <reviews>
   830694
  </reviews>
  <exclusive>
   yes
  </exclusive>
 </clothing>
</clothing-items>
